README.rst
setup.cfg
setup.py
iZettle/__init__.py
iZettle/iZettle.py
iZettle.egg-info/PKG-INFO
iZettle.egg-info/SOURCES.txt
iZettle.egg-info/dependency_links.txt
iZettle.egg-info/top_level.txt