Metadata-Version: 1.1
Name: iZettle
Version: 0.3.5
Summary: Unofficial python integration for iZettle API
Home-page: https://github.com/vilkasgroup/iZettle
Author: Aleksi Wikman
Author-email: aleksi@vilkas.fi
License: MIT license
Keywords: izettle,POS,Payment
Platform: UNKNOWN
Classifier: Intended Audience :: Developers
Classifier: License :: OSI Approved :: MIT License
Classifier: Natural Language :: English
Classifier: Programming Language :: Python :: 3.6
